setup.py
aid/__init__.py
aid/aid.py
aid/cli.py
aid/iptables.py
aid.egg-info/PKG-INFO
aid.egg-info/SOURCES.txt
aid.egg-info/dependency_links.txt
aid.egg-info/entry_points.txt
aid.egg-info/requires.txt
aid.egg-info/top_level.txt
test/test_aid.py
test/test_ipables.py