Metadata-Version: 1.1
Name: aid
Version: 0.1.0
Summary: library and scripts for interacting with ISP AID list
Home-page: https://github.com/utilitynerd/aid
Author: Mike Jones
Author-email: mikejones@security.berkeley.edu
License: Educational Community License, Version 2.0
Platform: UNKNOWN
Classifier: Development Status :: 4 - Beta
Classifier: Intended Audience :: System Administrators
Classifier: Topic :: System :: Networking :: Firewalls
Classifier: Topic :: System :: Systems Administration
Classifier: License :: OSI Approved
Classifier: Programming Language :: Python :: 2.7
Classifier: Programming Language :: Python :: 3.5
